{
  "hash": "75cd9288",
  "configHash": "1768714a",
  "lockfileHash": "506081bc",
  "browserHash": "8ad9dfb1",
  "optimized": {
    "react": {
      "src": "../../node_modules/react/index.js",
      "file": "react.js",
      "fileHash": "e3f3a2bd",
      "needsInterop": true
    },
    "react-dom": {
      "src": "../../node_modules/react-dom/index.js",
      "file": "react-dom.js",
      "fileHash": "4d9794cd",
      "needsInterop": true
    },
    "react/jsx-dev-runtime": {
      "src": "../../node_modules/react/jsx-dev-runtime.js",
      "file": "react_jsx-dev-runtime.js",
      "fileHash": "22a1ea9d",
      "needsInterop": true
    },
    "react/jsx-runtime": {
      "src": "../../node_modules/react/jsx-runtime.js",
      "file": "react_jsx-runtime.js",
      "fileHash": "24060478",
      "needsInterop": true
    },
    "react-dom/client": {
      "src": "../../node_modules/react-dom/client.js",
      "file": "react-dom_client.js",
      "fileHash": "51eeecf4",
      "needsInterop": true
    }
  },
  "chunks": {
    "chunk-V7SMXG7N": {
      "file": "chunk-V7SMXG7N.js"
    },
    "chunk-6Z5ALOK5": {
      "file": "chunk-6Z5ALOK5.js"
    }
  }
}